terratools/__init__.py
terratools/convert_files.py
terratools/data/gmt_coastlines_A10000.txt
terratools/example_data.py
terratools/flow_conversion.py
terratools/geographic.py
terratools/lookup_tables.py
terratools/plot.py
terratools/plume_detection.py
terratools/properties/__init__.py
terratools/properties/attenuation.py
terratools/properties/data/anderson_82.txt
terratools/properties/data/perplex_build_template.txt
terratools/properties/data/perplex_option.dat
terratools/properties/data/prem.txt
terratools/properties/perplex.py
terratools/properties/profiles.py
terratools/properties/utilities.py
terratools/terra_model.py
terratools-1.1.0.dist-info/LICENSE
terratools-1.1.0.dist-info/METADATA
terratools-1.1.0.dist-info/WHEEL
terratools-1.1.0.dist-info/RECORD
