Metadata-Version: 2.1
Name: terratools
Version: 1.1.0
Summary: Tools to read, analyse and visualise models written by the TERRA mantle convection code.
Home-page: https://github.com/mantle-convection-constrained/terratools
License: MIT
Author: James Panton
Author-email: pantonjc@cardiff.ac.uk
Requires-Python: >=3.8,<4.0
Classifier: License :: OSI Approved :: MIT License
Classifier: Operating System :: OS Independent
Classifier: Programming Language :: Python :: 3
Classifier: Programming Language :: Python :: 3.8
Classifier: Programming Language :: Python :: 3.9
Classifier: Programming Language :: Python :: 3.10
Classifier: Programming Language :: Python :: 3.11
Classifier: Programming Language :: Python :: 3.12
Requires-Dist: healpy (>=1.16.2,<2.0.0)
Requires-Dist: matplotlib (>=3.5,<4.0)
Requires-Dist: netcdf4 (>=1,<2)
Requires-Dist: numpy (>=1.23,<2.0)
Requires-Dist: pooch (>=1.7,<2.0)
Requires-Dist: scikit-learn (>=1.3.0,<2.0.0)
Requires-Dist: scipy (>=1.6,<2.0)
Project-URL: Documentation, https://readthedocs.org/projects/terratools
Project-URL: Repository, https://github.com/mantle-convection-constrained/terratools
